MANIFEST.in
RELEASE-VERSION
pavement.py
paver-minilib.zip
setup.py
version.py
signal_generator_board/__init__.py
signal_generator_board/Arduino/signal_generator_board/Config.h
signal_generator_board/Arduino/signal_generator_board/Config.h.skeleton
signal_generator_board/Arduino/signal_generator_board/Memory.h
signal_generator_board/Arduino/signal_generator_board/README.txt
signal_generator_board/Arduino/signal_generator_board/SConscript
signal_generator_board/Arduino/signal_generator_board/SignalGeneratorBoard.cpp
signal_generator_board/Arduino/signal_generator_board/SignalGeneratorBoard.h
signal_generator_board/Arduino/signal_generator_board/SignalGeneratorBoard.o
signal_generator_board/Arduino/signal_generator_board/signal_generator_board.ino
signal_generator_board/firmware/signal_generator_board.hex
wheeler.signal_generator_board.egg-info/PKG-INFO
wheeler.signal_generator_board.egg-info/SOURCES.txt
wheeler.signal_generator_board.egg-info/dependency_links.txt
wheeler.signal_generator_board.egg-info/requires.txt
wheeler.signal_generator_board.egg-info/top_level.txt