Metadata-Version: 1.0
Name: wheeler.signal-generator-board
Version: 0.3
Summary: Arduino-based signal generator board firmware and Python API.
Home-page: http://microfluidics.utoronto.ca/git/firmware___signal_generator_board.git
Author: Ryan Fobel
Author-email: ryan@fobel.net
License: GPLv2
Platform: UNKNOWN
